.gitignore
LICENSE
README.md
pyproject.toml
requirements.txt
setup.py
/home/dfnaiff/Danilo/NIDF/Projects/PyEquion2/pyequion/pyequion2/activity/coo_tensor_ops/coo_tensor_ops.c
docs/Makefile
docs/conf.py
docs/index.rst
docs/install.rst
docs/license.rst
docs/mainclasses.rst
docs/make.bat
docs/pyequion_logo.png
docs/reference.rst
docs/tutorials.rst
pyequion2/__init__.py
pyequion2/builder.py
pyequion2/constants.py
pyequion2/converters.py
pyequion2/equilibrium_system.py
pyequion2/logmaker.py
pyequion2/sequencer.py
pyequion2/solution.py
pyequion2/utils.py
pyequion2/water_properties.py
pyequion2.egg-info/PKG-INFO
pyequion2.egg-info/SOURCES.txt
pyequion2.egg-info/dependency_links.txt
pyequion2.egg-info/requires.txt
pyequion2.egg-info/top_level.txt
pyequion2/activity/__init__.py
pyequion2/activity/debye.py
pyequion2/activity/extended_debye.py
pyequion2/activity/ideal.py
pyequion2/activity/pitzer.py
pyequion2/activity/pitzer_sanity_assertions.py
pyequion2/activity/py_coo_tensor_ops.py
pyequion2/activity/coo_tensor_ops/coo_tensor_ops.c
pyequion2/activity/coo_tensor_ops/coo_tensor_ops.pyx
pyequion2/datamods/README
pyequion2/datamods/__init__.py
pyequion2/datamods/phreeqc.dat
pyequion2/datamods/pitzer.txt
pyequion2/datamods/pitzer_data.py
pyequion2/datamods/reactions_gases.py
pyequion2/datamods/reactions_irreversible.py
pyequion2/datamods/reactions_solids.py
pyequion2/datamods/reactions_solutions.py
pyequion2/datamods/species.py
pyequion2/datamods/temp.py
pyequion2/eqsolver/__init__.py
pyequion2/eqsolver/eqsolver.py
pyequion2/eqsolver/residual_functions.py
pyequion2/eqsolver/solvers.py
pyequion2/fugacity/__init__.py
pyequion2/fugacity/peng_robinson.py
pyequion2/fugacity/solve_cubic.py
pyequion2/gui/__init__.py
pyequion2/gui/initializer.py
pyequion2/gui/logmaker.py
pyequion2/gui/main.py
pyequion2/gui/run.py
pyequion2/gui/seqsolution.py
pyequion2/gui/solution.py
pyequion2/gui/solver.py
pyequion2/gui/images/pyequion_logo.png
pyequion2/interface/__init__.py
pyequion2/interface/diffusion_coefficients.py
pyequion2/interface/interface_functions.py
pyequion2/interface/interface_solution.py
pyequion2/interface/interface_system.py
