Metadata-Version: 2.1
Name: pyequion2
Version: 0.0.6.3
Summary: Chemical equilibrium for electrolytes in pure python
Home-page: https://github.com/pyequion/pyequion2/
Author: PyEquion
License: UNKNOWN
Platform: UNKNOWN
Classifier: Programming Language :: Python :: 3
Classifier: License :: OSI Approved :: BSD License
Classifier: Operating System :: OS Independent
Requires-Python: >=3.6
License-File: LICENSE
